cli_tool/__init__.py
cli_tool/click_aws.py
cli_tool/click_demo.py
cli_tool/click_test.py
devops_cli_ericli-0.1.7.dist-info/METADATA
devops_cli_ericli-0.1.7.dist-info/WHEEL
devops_cli_ericli-0.1.7.dist-info/entry_points.txt
devops_cli_ericli-0.1.7.dist-info/top_level.txt
devops_cli_ericli-0.1.7.dist-info/RECORD
