Metadata-Version: 2.1
Name: devops-cli-ericli
Version: 0.1.7
Summary: DevOps Tool
Home-page: https://test.com
Author: Michael Su
Author-email: michaelsu2014@gmail.com
License: MIT
Platform: UNKNOWN
Classifier: Development Status :: 5 - Production/Stable
Classifier: Intended Audience :: Developers
Classifier: Operating System :: Unix
Classifier: Operating System :: POSIX
Classifier: Programming Language :: Python
Classifier: Programming Language :: Python :: 3.7
Classifier: Topic :: Utilities
Requires-Dist: boto3
Requires-Dist: click
Requires-Dist: requests
